xdevs/__init__.py
xdevs/factory.py
xdevs/models.py
xdevs/rt.py
xdevs/sim.py
xdevs/abc/__init__.py
xdevs/abc/celldevs.py
xdevs/abc/handler.py
xdevs/abc/transducer.py
xdevs/celldevs/__init__.py
xdevs/celldevs/cell.py
xdevs/celldevs/coupled.py
xdevs/celldevs/grid.py
xdevs/celldevs/inout.py
xdevs/examples/__init__.py
xdevs/examples/celldevs_sir/__init__.py
xdevs/examples/celldevs_sir/main.py
xdevs/examples/celldevs_sir/sir_cell.py
xdevs/examples/celldevs_sir/sir_coupled.py
xdevs/examples/celldevs_sir/sir_sink.py
xdevs/examples/devstone/__init__.py
xdevs/examples/devstone/devstone.py
xdevs/examples/devstone/generator.py
xdevs/examples/devstone/main.py
xdevs/examples/devstone/pystone.py
xdevs/examples/gpt/__init__.py
xdevs/examples/gpt/efp.py
xdevs/examples/gpt/gpt_rt_ih_oh_sim.py
xdevs/examples/gpt/gpt_rt_ih_sim.py
xdevs/examples/gpt/gpt_rt_oh_sim.py
xdevs/examples/gpt/gpt_rt_sim.py
xdevs/examples/gpt/gpt_v_sim.py
xdevs/examples/gpt/models.py
xdevs/examples/json/__init__.py
xdevs/examples/json/json2xdevs_example.py
xdevs/examples/store/1_vt_simulation.py
xdevs/examples/store/2_rt_simulation_csv_output_handler.py
xdevs/examples/store/3_rt_simulation_tcp_input_handler.py
xdevs/examples/store/4_1_rt_simulation_mqtt_input_handler.py
xdevs/examples/store/4_2_rt_simulation_mqtt_output_handler.py
xdevs/examples/store/__init__.py
xdevs/examples/store/system_clients.py
xdevs/examples/store/system_employees.py
xdevs/examples/store/system_queue.py
xdevs/examples/store/models/__init__.py
xdevs/examples/store/models/clients.py
xdevs/examples/store/models/employee.py
xdevs/examples/store/models/msg.py
xdevs/examples/store/models/queue.py
xdevs/examples/store/models/store.py
xdevs/plugins/__init__.py
xdevs/plugins/celldevs_outputs/__init__.py
xdevs/plugins/celldevs_outputs/hybrid.py
xdevs/plugins/celldevs_outputs/inertial.py
xdevs/plugins/celldevs_outputs/transport.py
xdevs/plugins/input_handlers/__init__.py
xdevs/plugins/input_handlers/bad_dependencies.py
xdevs-3.0.0.dist-info/LICENSE.txt
xdevs-3.0.0.dist-info/METADATA
xdevs-3.0.0.dist-info/WHEEL
xdevs-3.0.0.dist-info/entry_points.txt
xdevs-3.0.0.dist-info/top_level.txt
xdevs-3.0.0.dist-info/RECORD
