Metadata-Version: 2.1
Name: xdevs
Version: 3.0.0
Summary: xDEVS M&S framework
Author: Román Cárdenas, Óscar Fernández Sebastián, Kevin Henares, José L. Risco-Martín
Maintainer-email: Román Cárdenas <r.cardenas@upm.es>
License: GNU GENERAL PUBLIC LICENSE
Project-URL: Homepage, https://github.com/iscar-ucm/xdevs
Project-URL: Documentation, https://github.com/iscar-ucm/xdevs
Project-URL: Repository, https://github.com/iscar-ucm/xdevs.py.git
Project-URL: Bug Tracker, https://github.com/iscar-ucm/xdevs.py/issues
Project-URL: Changelog, https://github.com/iscar-ucm/xdevs.py/blob/main/CHANGELOG.md
Keywords: DEVS,modeling,simulation
Requires-Python: >=3.9
License-File: LICENSE.txt
Provides-Extra: elasticsearch
Requires-Dist: elasticsearch ; extra == 'elasticsearch'
Provides-Extra: mqtt
Requires-Dist: paho-mqtt ; extra == 'mqtt'
Provides-Extra: sql
Requires-Dist: sqlalchemy ; extra == 'sql'
